README.md
setup.cfg
setup.py
vdm3/__init__.py
vdm3/components.py
vdm3/vdm.py
vdm3.egg-info/PKG-INFO
vdm3.egg-info/SOURCES.txt
vdm3.egg-info/dependency_links.txt
vdm3.egg-info/requires.txt
vdm3.egg-info/top_level.txt