Metadata-Version: 2.1
Name: vdm3
Version: 0.0.1
Summary: Use Value Difference Metric to find distance between categorical features
Home-page: https://github.com/esmondhkchu/vdm3
Author: Esmond Chu
Author-email: chuhke@gmail.com
License: MIT
Download-URL: https://github.com/esmondhkchu/vdm3/archive/v0.0.1.tar.gz
Keywords: statistics,machine learning,distance
Platform: UNKNOWN
Classifier: Development Status :: 3 - Alpha
Classifier: Intended Audience :: Developers
Classifier: Topic :: Software Development :: Build Tools
Classifier: License :: OSI Approved :: MIT License
Classifier: Programming Language :: Python :: 3
Classifier: Programming Language :: Python :: 3.4
Classifier: Programming Language :: Python :: 3.5
Classifier: Programming Language :: Python :: 3.6
Classifier: Programming Language :: Python :: 3.7
Classifier: Programming Language :: Python :: 3.8
